CHANGELOG.md
compressnets/__init__.py
compressnets/compression.py
compressnets/datafiles/__init__.py
compressnets/datafiles/sample_fig.pdf
compressnets/datafiles/sample_fig.png
compressnets/datafiles/sample_network
compressnets/demos.py
compressnets/network.py
compressnets/solvers.py
tests/__init__.py
tests/test_compression.py
tests/test_network.py
compressnets-1.1.2.dist-info/LICENSE.txt
compressnets-1.1.2.dist-info/WHEEL
compressnets-1.1.2.dist-info/METADATA
compressnets-1.1.2.dist-info/RECORD
