Metadata-Version: 2.1
Name: compressnets
Version: 1.1.2
Summary: Package for temporal network data compression
Home-page: https://github.com/andrea-allen/compressnets
License: BSD-3
Keywords: python,compressnets,networks,compression
Author: Andrea Allen
Author-email: andrea2allen@gmail.com
Requires-Python: >=3.8,<3.11
Classifier: Development Status :: 4 - Beta
Classifier: Intended Audience :: Science/Research
Classifier: License :: Other/Proprietary License
Classifier: Operating System :: MacOS :: MacOS X
Classifier: Operating System :: Microsoft :: Windows
Classifier: Programming Language :: Python :: 3
Classifier: Programming Language :: Python :: 3.8
Classifier: Programming Language :: Python :: 3.9
Classifier: Programming Language :: Python :: 3.10
Classifier: Programming Language :: Python :: 3
